avideo_dl/__init__.py
avideo_dl/aa.py
avideo_dl/downloader.py
avideo_dl/extractor/__init__.py
avideo_dl/extractor/modules/__init__.py
avideo_dl/extractor/modules/_pornhub.py
avideo_dl/extractor/modules/fc2.py
avideo_dl/extractor/modules/redtube.py
avideo_dl/extractor/modules/tube8.py
avideo_dl/extractor/modules/xvideos.py
avideo_dl/scripts/__init__.py
avideo_dl/scripts/command.py
avideo_dl/utils.py
avideo_dl-0.1.2.dist-info/entry_points.txt
avideo_dl-0.1.2.dist-info/LICENSE
avideo_dl-0.1.2.dist-info/WHEEL
avideo_dl-0.1.2.dist-info/METADATA
avideo_dl-0.1.2.dist-info/RECORD
