Metadata-Version: 2.1
Name: avideo-dl
Version: 0.1.2
Summary: Fast adult video downloader with no dependent third party libraries.
Home-page: https://github.com/ksk001100/avideo-dl
License: MIT
Author: ksk001100
Author-email: hm.pudding0715@gmail.com
Requires-Python: >=3.6,<4.0
Classifier: License :: OSI Approved :: MIT License
Classifier: Programming Language :: Python :: 3
Classifier: Programming Language :: Python :: 3.6
Classifier: Programming Language :: Python :: 3.7
Classifier: Programming Language :: Python :: 3.8
Project-URL: Repository, https://github.com/ksk001100/avideo-dl
